LICENSE
MANIFEST.in
README.md
quicktest.py
settings_test.py
setup.py
django_vkontakte_ads.egg-info/PKG-INFO
django_vkontakte_ads.egg-info/SOURCES.txt
django_vkontakte_ads.egg-info/dependency_links.txt
django_vkontakte_ads.egg-info/not-zip-safe
django_vkontakte_ads.egg-info/requires.txt
django_vkontakte_ads.egg-info/top_level.txt
vkontakte_ads/.DS_Store
vkontakte_ads/__init__.py
vkontakte_ads/__init__.pyc
vkontakte_ads/admin.py
vkontakte_ads/admin.pyc
vkontakte_ads/factories.py
vkontakte_ads/factories.pyc
vkontakte_ads/lookups.py
vkontakte_ads/models.py
vkontakte_ads/models.pyc
vkontakte_ads/signals.py
vkontakte_ads/signals.pyc
vkontakte_ads/tests.py
vkontakte_ads/tests.pyc
vkontakte_ads/views.py
vkontakte_ads/views.pyc
vkontakte_ads/management/__init__.py
vkontakte_ads/management/__init__.pyc
vkontakte_ads/management/commands/__init__.py
vkontakte_ads/management/commands/fetch_vkontakte_ads_data.py
vkontakte_ads/migrations/0001_initial.py
vkontakte_ads/migrations/0001_initial.pyc
vkontakte_ads/migrations/__init__.py
vkontakte_ads/migrations/__init__.pyc
vkontakte_ads/static/.DS_Store
vkontakte_ads/static/vkontakte_ads/.DS_Store
vkontakte_ads/static/vkontakte_ads/img/loading-indicator.gif
vkontakte_ads/static/vkontakte_ads/img/test.gif
vkontakte_ads/static/vkontakte_ads/js/admin.js